cran_diff/__init__.py
cran_diff/cran_archive.py
cran_diff/cran_parser.py
cran_diff/cran_parsing_functions.py
cran_diff/file_functions.py
cran_diff/filenames.py
cran_diff/pkg_parsing_functions.py
cran_diff/rcom.py
cran_diff/tuples.py
cran_diff/urls.py
cran_diff-0.1.16.dist-info/WHEEL
cran_diff-0.1.16.dist-info/METADATA
cran_diff-0.1.16.dist-info/RECORD
